docbooktoxtm/__init__.py
docbooktoxtm/__main__.py
docbooktoxtm/bookclasses.py
docbooktoxtm/config.py
docbooktoxtm/functions.py
docbooktoxtm/logconfig.py
docbooktoxtm/main.py
docbooktoxtm-1.2.1.dist-info/entry_points.txt
docbooktoxtm-1.2.1.dist-info/WHEEL
docbooktoxtm-1.2.1.dist-info/METADATA
docbooktoxtm-1.2.1.dist-info/RECORD
