Metadata-Version: 2.1
Name: docbooktoxtm
Version: 1.2.1
Summary: 
Author: Ryan O'Rourke
Author-email: ryan.orourke@welocalize.com
Requires-Python: >=3.8,<4.0
Classifier: Programming Language :: Python :: 3
Classifier: Programming Language :: Python :: 3.8
Requires-Dist: PyGithub (>=1.51,<2.0)
Requires-Dist: fuzzywuzzy (>=0.18.0,<0.19.0)
Requires-Dist: lxml (>=4.5.1,<5.0.0)
Requires-Dist: pydantic (>=1.5.1,<2.0.0)
Requires-Dist: python-Levenshtein (>=0.12.0,<0.13.0)
Requires-Dist: requests (>=2.24.0,<3.0.0)
Requires-Dist: typer[all] (>=0.3.0,<0.4.0)
Requires-Dist: xmltodict (>=0.12.0,<0.13.0)
